MEDS_tabular_automl/__init__.py
MEDS_tabular_automl/describe_codes.py
MEDS_tabular_automl/file_name.py
MEDS_tabular_automl/generate_static_features.py
MEDS_tabular_automl/generate_summarized_reps.py
MEDS_tabular_automl/generate_ts_features.py
MEDS_tabular_automl/mapper.py
MEDS_tabular_automl/utils.py
MEDS_tabular_automl/configs/__init__.py
MEDS_tabular_automl/configs/default.yaml
MEDS_tabular_automl/configs/describe_codes.yaml
MEDS_tabular_automl/configs/launch_xgboost.yaml
MEDS_tabular_automl/configs/tabularization.yaml
MEDS_tabular_automl/configs/task_specific_caching.yaml
MEDS_tabular_automl/configs/tmp.yaml.yaml
MEDS_tabular_automl/configs/tabularization/__init__.py
MEDS_tabular_automl/configs/tabularization/default.yaml
MEDS_tabular_automl/scripts/__init__.py
MEDS_tabular_automl/scripts/cache_task.py
MEDS_tabular_automl/scripts/describe_codes.py
MEDS_tabular_automl/scripts/launch_xgboost.py
MEDS_tabular_automl/scripts/sweep_xgboost.py
MEDS_tabular_automl/scripts/tabularize_static.py
MEDS_tabular_automl/scripts/tabularize_time_series.py
MEDS_tabularization-0.0.1.dist-info/LICENSE
MEDS_tabularization-0.0.1.dist-info/METADATA
MEDS_tabularization-0.0.1.dist-info/WHEEL
MEDS_tabularization-0.0.1.dist-info/entry_points.txt
MEDS_tabularization-0.0.1.dist-info/top_level.txt
MEDS_tabularization-0.0.1.dist-info/RECORD
