Metadata-Version: 2.1
Name: MEDS_tabularization
Version: 0.0.1
Summary: Scalable Tabularization of MEDS format Time-Series data
Author-email: Matthew McDermott <mattmcdermott8@gmail.com>, Nassim Oufattole <noufattole@gmail.com>, Teya Bergamaschi <teyabergamaschi@gmail.com>
Project-URL: Homepage, https://github.com/mmcdermott/MEDS_Tabular_AutoML
Project-URL: Issues, https://github.com/mmcdermott/MEDS_Tabular_AutoML/issues
Classifier: Programming Language :: Python :: 3
Classifier: License :: OSI Approved :: MIT License
Classifier: Operating System :: OS Independent
Requires-Python: >=3.12
License-File: LICENSE
Requires-Dist: polars
Requires-Dist: pyarrow
Requires-Dist: loguru
Requires-Dist: hydra-core
Requires-Dist: numpy
Requires-Dist: scipy
Requires-Dist: pandas
Requires-Dist: tqdm
Requires-Dist: xgboost
Requires-Dist: scikit-learn
Requires-Dist: hydra-optuna-sweeper
Requires-Dist: hydra-joblib-launcher
Requires-Dist: ml-mixins
Provides-Extra: dev
Requires-Dist: pre-commit ; extra == 'dev'
Provides-Extra: profiling
Requires-Dist: mprofile ; extra == 'profiling'
Requires-Dist: matplotlib ; extra == 'profiling'
Provides-Extra: tests
Requires-Dist: pytest ; extra == 'tests'
Requires-Dist: pytest-cov ; extra == 'tests'
Requires-Dist: rootutils ; extra == 'tests'
